{
  "updatedAt": 1778462752587,
  "source": "Binance P2P web endpoint",
  "asset": "USDT",
  "prices": {
    "OMR": {
      "BUY": {
        "price": 0.391,
        "pickedIndex": 1,
        "availableRows": 10,
        "advNo": "12881730817955667968",
        "nickName": "Ali-Crypto22",
        "minSingleTransAmount": "200",
        "maxSingleTransAmount": "2500",
        "tradeMethods": [
          "Bank Transfer"
        ]
      },
      "SELL": {
        "price": 0.388,
        "pickedIndex": 1,
        "availableRows": 10,
        "advNo": "12794776545260261376",
        "nickName": "mazinalhmdani",
        "minSingleTransAmount": "139",
        "maxSingleTransAmount": "1000",
        "tradeMethods": [
          "Bank Muscat",
          "Airtime Mobile Top-Up"
        ]
      }
    },
    "EGP": {
      "BUY": {
        "price": 53.28,
        "pickedIndex": 1,
        "availableRows": 11,
        "advNo": "12886950067427454976",
        "nickName": "7araka1",
        "minSingleTransAmount": "5100",
        "maxSingleTransAmount": "5300",
        "tradeMethods": [
          "InstaPay"
        ]
      },
      "SELL": {
        "price": 53.85,
        "pickedIndex": 1,
        "availableRows": 11,
        "advNo": "12854885330261327872",
        "nickName": "Falcon111 ",
        "minSingleTransAmount": "15000",
        "maxSingleTransAmount": "15001",
        "tradeMethods": [
          "Vodafone cash"
        ]
      }
    },
    "AED": {
      "BUY": {
        "price": 3.684,
        "pickedIndex": 1,
        "availableRows": 10,
        "advNo": "12881426636518281216",
        "nickName": "Target-destroyed",
        "minSingleTransAmount": "10000",
        "maxSingleTransAmount": "19335",
        "tradeMethods": [
          "Bank Transfer (Middle East)",
          "ADIB: Abu Dhabi Islamic Bank"
        ]
      },
      "SELL": {
        "price": 3.672,
        "pickedIndex": 1,
        "availableRows": 10,
        "advNo": "12886853397596499968",
        "nickName": "My-love-Ethiopia",
        "minSingleTransAmount": "1000",
        "maxSingleTransAmount": "5000",
        "tradeMethods": [
          "ADIB: Abu Dhabi Islamic Bank"
        ]
      }
    },
    "SAR": {
      "BUY": {
        "price": 3.81,
        "pickedIndex": 1,
        "availableRows": 11,
        "advNo": "13875119792553488384",
        "nickName": "usdt_7ksa",
        "minSingleTransAmount": "10000",
        "maxSingleTransAmount": "100000",
        "tradeMethods": [
          "Transfers with specific bank",
          "Al Rajhi Bank",
          "Saudi National Bank (AlAhli Bank)"
        ]
      },
      "SELL": {
        "price": 3.86,
        "pickedIndex": 1,
        "availableRows": 11,
        "advNo": "12864248375439060992",
        "nickName": "WELCOME ALL",
        "minSingleTransAmount": "30",
        "maxSingleTransAmount": "30",
        "tradeMethods": [
          "Bank Transfer",
          "Al Rajhi Bank"
        ]
      }
    },
    "USD": {
      "BUY": {
        "price": 1.0,
        "pickedIndex": 1,
        "availableRows": 11,
        "advNo": "12556206845790932992",
        "nickName": "誌得其樂",
        "minSingleTransAmount": "15",
        "maxSingleTransAmount": "1500",
        "tradeMethods": [
          "Bank Transfer (Taiwan)"
        ]
      },
      "SELL": {
        "price": 1.1,
        "pickedIndex": 1,
        "availableRows": 11,
        "advNo": "12885343937109921792",
        "nickName": "SKTradersZ",
        "minSingleTransAmount": "15",
        "maxSingleTransAmount": "1500",
        "tradeMethods": [
          "Google Pay (GPay)",
          "IMPS",
          "stc pay",
          "PhonePe",
          "Paytm"
        ]
      }
    },
    "EUR": {
      "BUY": {
        "price": 0.856,
        "pickedIndex": 1,
        "availableRows": 10,
        "advNo": "13864797561543344128",
        "nickName": "TEZER_Exchange",
        "minSingleTransAmount": "250",
        "maxSingleTransAmount": "20000",
        "tradeMethods": [
          "Bank Transfer",
          "SEPA Instant",
          "SEPA (EU) bank transfer",
          "N26",
          "Bunq"
        ]
      },
      "SELL": {
        "price": 0.862,
        "pickedIndex": 1,
        "availableRows": 11,
        "advNo": "12886484767668236288",
        "nickName": "Payoneer2Wise-P2P",
        "minSingleTransAmount": "125",
        "maxSingleTransAmount": "126",
        "tradeMethods": [
          "Dukascopy Bank"
        ]
      }
    }
  }
}