{
  "updatedAt": 1775023795152,
  "source": "Binance P2P web endpoint",
  "asset": "USDT",
  "prices": {
    "OMR": {
      "BUY": {
        "price": 0.393,
        "pickedIndex": 1,
        "availableRows": 10,
        "advNo": "12862761742054543360",
        "nickName": "Munther_94",
        "minSingleTransAmount": "150",
        "maxSingleTransAmount": "2500",
        "tradeMethods": [
          "National Bank of Oman",
          "Ahlibank",
          "Sohar International"
        ]
      },
      "SELL": {
        "price": 0.391,
        "pickedIndex": 1,
        "availableRows": 11,
        "advNo": "12839823669546295296",
        "nickName": "ALZANATY-2017",
        "minSingleTransAmount": "10",
        "maxSingleTransAmount": "200",
        "tradeMethods": [
          "Bank Muscat"
        ]
      }
    },
    "EGP": {
      "BUY": {
        "price": 56.29,
        "pickedIndex": 1,
        "availableRows": 10,
        "advNo": "12870515037406236672",
        "nickName": "Locus_Crypto",
        "minSingleTransAmount": "10000",
        "maxSingleTransAmount": "500000",
        "tradeMethods": [
          "InstaPay"
        ]
      },
      "SELL": {
        "price": 56.92,
        "pickedIndex": 1,
        "availableRows": 11,
        "advNo": "12854564115654520832",
        "nickName": "The captain 1",
        "minSingleTransAmount": "6000",
        "maxSingleTransAmount": "6001",
        "tradeMethods": [
          "Vodafone cash"
        ]
      }
    },
    "AED": {
      "BUY": {
        "price": 3.706,
        "pickedIndex": 1,
        "availableRows": 10,
        "advNo": "12872539371522543616",
        "nickName": "Rehmanlatif",
        "minSingleTransAmount": "5000",
        "maxSingleTransAmount": "5680",
        "tradeMethods": [
          "Bank Transfer"
        ]
      },
      "SELL": {
        "price": 3.69,
        "pickedIndex": 1,
        "availableRows": 10,
        "advNo": "12704228689228431360",
        "nickName": "Piplumsh",
        "minSingleTransAmount": "5999",
        "maxSingleTransAmount": "6000",
        "tradeMethods": [
          "Cash Deposit to Bank"
        ]
      }
    },
    "SAR": {
      "BUY": {
        "price": 3.81,
        "pickedIndex": 1,
        "availableRows": 11,
        "advNo": "13872327691776679936",
        "nickName": "Naif_Ahmed",
        "minSingleTransAmount": "10000",
        "maxSingleTransAmount": "10000000",
        "tradeMethods": [
          "Saudi National Bank (AlAhli Bank)",
          "Alinma Bank",
          "Riyad Bank",
          "Al Rajhi Bank",
          "Bank Transfer"
        ]
      },
      "SELL": {
        "price": 3.88,
        "pickedIndex": 1,
        "availableRows": 11,
        "advNo": "12865885353843425280",
        "nickName": "Ahmed_ezzaldain",
        "minSingleTransAmount": "6700",
        "maxSingleTransAmount": "6800",
        "tradeMethods": [
          "urpay"
        ]
      }
    },
    "USD": {
      "BUY": {
        "price": 1.0,
        "pickedIndex": 1,
        "availableRows": 11,
        "advNo": "12556206845790932992",
        "nickName": "誌得其樂",
        "minSingleTransAmount": "15",
        "maxSingleTransAmount": "1500",
        "tradeMethods": [
          "Bank Transfer (Taiwan)"
        ]
      },
      "SELL": {
        "price": 1.1,
        "pickedIndex": 1,
        "availableRows": 11,
        "advNo": "12837566109293064192",
        "nickName": "Rurisyz",
        "minSingleTransAmount": "500",
        "maxSingleTransAmount": "6800",
        "tradeMethods": [
          "SEA Bank"
        ]
      }
    },
    "EUR": {
      "BUY": {
        "price": 0.87,
        "pickedIndex": 1,
        "availableRows": 10,
        "advNo": "13819385243161866240",
        "nickName": "PLUMEX",
        "minSingleTransAmount": "100",
        "maxSingleTransAmount": "100000",
        "tradeMethods": [
          "ZEN",
          "Bank Transfer",
          "SEPA (EU) bank transfer",
          "SEPA Instant",
          "N26"
        ]
      },
      "SELL": {
        "price": 0.918,
        "pickedIndex": 1,
        "availableRows": 11,
        "advNo": "12870187555855925248",
        "nickName": "Anyelithcuellar",
        "minSingleTransAmount": "29800",
        "maxSingleTransAmount": "29900",
        "tradeMethods": [
          "Banco Santander (Spain)",
          "SEPA Instant",
          "N26",
          "BBVA",
          "ING"
        ]
      }
    }
  }
}