{
  "updatedAt": 1774726653753,
  "source": "Binance P2P web endpoint",
  "asset": "USDT",
  "prices": {
    "OMR": {
      "BUY": {
        "price": 0.393,
        "pickedIndex": 1,
        "availableRows": 11,
        "advNo": "12859733042922000384",
        "nickName": "Ali-Crypto22",
        "minSingleTransAmount": "300",
        "maxSingleTransAmount": "2500",
        "tradeMethods": [
          "Bank Muscat",
          "Sohar International",
          "Ahlibank"
        ]
      },
      "SELL": {
        "price": 0.404,
        "pickedIndex": 1,
        "availableRows": 11,
        "advNo": "12870541286956449792",
        "nickName": "Cryptoversee",
        "minSingleTransAmount": "600",
        "maxSingleTransAmount": "2500",
        "tradeMethods": [
          "Bank Transfer"
        ]
      }
    },
    "EGP": {
      "BUY": {
        "price": 53.23,
        "pickedIndex": 1,
        "availableRows": 11,
        "advNo": "13699699591856562176",
        "nickName": "Abouyousef",
        "minSingleTransAmount": "20000",
        "maxSingleTransAmount": "20001",
        "tradeMethods": [
          "Bank Transfer",
          "Alex Bank",
          "Instant Transfer"
        ]
      },
      "SELL": {
        "price": 53.8,
        "pickedIndex": 1,
        "availableRows": 11,
        "advNo": "12855477489893044224",
        "nickName": "KAGE_NO1",
        "minSingleTransAmount": "90",
        "maxSingleTransAmount": "91",
        "tradeMethods": [
          "Vodafone cash",
          "Etisalat Cash",
          "Orange Cash",
          "InstaPay"
        ]
      }
    },
    "AED": {
      "BUY": {
        "price": 3.711,
        "pickedIndex": 1,
        "availableRows": 10,
        "advNo": "12759233664740556800",
        "nickName": "McLaren19",
        "minSingleTransAmount": "5500",
        "maxSingleTransAmount": "25000",
        "tradeMethods": [
          "Bank Transfer"
        ]
      },
      "SELL": {
        "price": 3.703,
        "pickedIndex": 1,
        "availableRows": 10,
        "advNo": "12866490253035233280",
        "nickName": "Aani-BankP2P",
        "minSingleTransAmount": "1000",
        "maxSingleTransAmount": "140000",
        "tradeMethods": [
          "Cash Deposit to Bank",
          "ADIB: Abu Dhabi Islamic Bank"
        ]
      }
    },
    "SAR": {
      "BUY": {
        "price": 3.83,
        "pickedIndex": 1,
        "availableRows": 11,
        "advNo": "12867924819763101696",
        "nickName": "usdt_7ksa",
        "minSingleTransAmount": "10000",
        "maxSingleTransAmount": "75000",
        "tradeMethods": [
          "Transfers with specific bank"
        ]
      },
      "SELL": {
        "price": 3.87,
        "pickedIndex": 1,
        "availableRows": 11,
        "advNo": "12870476805960204288",
        "nickName": "User-ac76a",
        "minSingleTransAmount": "2198",
        "maxSingleTransAmount": "2199",
        "tradeMethods": [
          "Bank Transfer",
          "stc pay",
          "Alinma Bank",
          "Al Rajhi Bank",
          "Saudi National Bank (AlAhli Bank)"
        ]
      }
    },
    "USD": {
      "BUY": {
        "price": 1.0,
        "pickedIndex": 1,
        "availableRows": 11,
        "advNo": "12556206845790932992",
        "nickName": "誌得其樂",
        "minSingleTransAmount": "15",
        "maxSingleTransAmount": "1500",
        "tradeMethods": [
          "Bank Transfer (Taiwan)"
        ]
      },
      "SELL": {
        "price": 1.1,
        "pickedIndex": 1,
        "availableRows": 11,
        "advNo": "12837566109293064192",
        "nickName": "Rurisyz",
        "minSingleTransAmount": "500",
        "maxSingleTransAmount": "6800",
        "tradeMethods": [
          "SEA Bank"
        ]
      }
    },
    "EUR": {
      "BUY": {
        "price": 0.873,
        "pickedIndex": 1,
        "availableRows": 10,
        "advNo": "13864797426777096192",
        "nickName": "TEZER_Exchange",
        "minSingleTransAmount": "250",
        "maxSingleTransAmount": "10000",
        "tradeMethods": [
          "Bank Transfer",
          "SEPA Instant",
          "SEPA (EU) bank transfer",
          "BBVA",
          "Paysera"
        ]
      },
      "SELL": {
        "price": 0.918,
        "pickedIndex": 1,
        "availableRows": 11,
        "advNo": "12866233481592946688",
        "nickName": "RivasMarcanoTitular",
        "minSingleTransAmount": "29800",
        "maxSingleTransAmount": "29900",
        "tradeMethods": [
          "Banco Santander (Spain)",
          "SEPA Instant",
          "N26",
          "BBVA",
          "ING"
        ]
      }
    }
  }
}