{
  "updatedAt": 1784362357543,
  "source": "Binance P2P web endpoint",
  "asset": "USDT",
  "prices": {
    "OMR": {
      "BUY": {
        "price": 0.389,
        "pickedIndex": 1,
        "availableRows": 11,
        "advNo": "12903100155889836032",
        "nickName": "OMAN_OTC_SERVICE",
        "minSingleTransAmount": "300",
        "maxSingleTransAmount": "2500",
        "tradeMethods": [
          "Bank Muscat",
          "Ahlibank"
        ]
      },
      "SELL": {
        "price": 0.388,
        "pickedIndex": 1,
        "availableRows": 11,
        "advNo": "12890037120218238976",
        "nickName": "P2P-8c6ed9fi",
        "minSingleTransAmount": "500",
        "maxSingleTransAmount": "2500",
        "tradeMethods": [
          "Bank Muscat",
          "Bank Dhofar"
        ]
      }
    },
    "EGP": {
      "BUY": {
        "price": 51.27,
        "pickedIndex": 1,
        "availableRows": 11,
        "advNo": "12872086274787868672",
        "nickName": "احمد موحسين",
        "minSingleTransAmount": "3000",
        "maxSingleTransAmount": "500000",
        "tradeMethods": [
          "InstaPay"
        ]
      },
      "SELL": {
        "price": 51.81,
        "pickedIndex": 1,
        "availableRows": 11,
        "advNo": "12877960340499918848",
        "nickName": "Elbasha-Online",
        "minSingleTransAmount": "10000",
        "maxSingleTransAmount": "10001",
        "tradeMethods": [
          "Vodafone cash"
        ]
      }
    },
    "AED": {
      "BUY": {
        "price": 3.67,
        "pickedIndex": 1,
        "availableRows": 10,
        "advNo": "13871859053140672512",
        "nickName": "DXB_DEALS",
        "minSingleTransAmount": "20000",
        "maxSingleTransAmount": "600000",
        "tradeMethods": [
          "ADIB: Abu Dhabi Islamic Bank",
          "Bank Transfer"
        ]
      },
      "SELL": {
        "price": 3.66,
        "pickedIndex": 1,
        "availableRows": 10,
        "advNo": "12891927007780589568",
        "nickName": "KING_USDT12",
        "minSingleTransAmount": "7699",
        "maxSingleTransAmount": "7700",
        "tradeMethods": [
          "Bank Transfer",
          "Abu Dhabi Commercial Bank ADCB"
        ]
      }
    },
    "SAR": {
      "BUY": {
        "price": 3.81,
        "pickedIndex": 1,
        "availableRows": 11,
        "advNo": "13897311917314912256",
        "nickName": "usdt_7ksa",
        "minSingleTransAmount": "10000",
        "maxSingleTransAmount": "150000",
        "tradeMethods": [
          "Transfers with specific bank",
          "Al Rajhi Bank",
          "Saudi National Bank (AlAhli Bank)"
        ]
      },
      "SELL": {
        "price": 3.85,
        "pickedIndex": 1,
        "availableRows": 11,
        "advNo": "12909290390208290816",
        "nickName": "salman50i",
        "minSingleTransAmount": "10",
        "maxSingleTransAmount": "60",
        "tradeMethods": [
          "Bank Transfer",
          "Al Rajhi Bank"
        ]
      }
    },
    "USD": {
      "BUY": {
        "price": 0.902,
        "pickedIndex": 1,
        "availableRows": 11,
        "advNo": "12911658370231492608",
        "nickName": "nime96",
        "minSingleTransAmount": "50",
        "maxSingleTransAmount": "2000",
        "tradeMethods": [
          "Paysera"
        ]
      },
      "SELL": {
        "price": 1.1,
        "pickedIndex": 1,
        "availableRows": 11,
        "advNo": "12899232431567327232",
        "nickName": "SunShine2908",
        "minSingleTransAmount": "100",
        "maxSingleTransAmount": "700",
        "tradeMethods": [
          "Zelle"
        ]
      }
    },
    "EUR": {
      "BUY": {
        "price": 0.885,
        "pickedIndex": 1,
        "availableRows": 10,
        "advNo": "13810757867699556352",
        "nickName": "CryptoLandGroup",
        "minSingleTransAmount": "2199",
        "maxSingleTransAmount": "2200",
        "tradeMethods": [
          "CaixaBank (Spain)"
        ]
      },
      "SELL": {
        "price": 0.89,
        "pickedIndex": 1,
        "availableRows": 11,
        "advNo": "12911452175597019136",
        "nickName": "Cambios12345",
        "minSingleTransAmount": "400",
        "maxSingleTransAmount": "500",
        "tradeMethods": [
          "Banco Santander (Spain)"
        ]
      }
    }
  }
}