{
  "updatedAt": 1783699224104,
  "source": "Binance P2P web endpoint",
  "asset": "USDT",
  "prices": {
    "OMR": {
      "BUY": {
        "price": 0.388,
        "pickedIndex": 1,
        "availableRows": 11,
        "advNo": "12887881445201272832",
        "nickName": "BTC_OMAN88",
        "minSingleTransAmount": "100",
        "maxSingleTransAmount": "2500",
        "tradeMethods": [
          "Sohar International"
        ]
      },
      "SELL": {
        "price": 0.391,
        "pickedIndex": 1,
        "availableRows": 11,
        "advNo": "12908812741908590592",
        "nickName": "Abdullah20002",
        "minSingleTransAmount": "2000",
        "maxSingleTransAmount": "2500",
        "tradeMethods": [
          "Bank Transfer"
        ]
      }
    },
    "EGP": {
      "BUY": {
        "price": 50.25,
        "pickedIndex": 1,
        "availableRows": 11,
        "advNo": "12905758797289123840",
        "nickName": "BZRA17MB",
        "minSingleTransAmount": "2027",
        "maxSingleTransAmount": "2030",
        "tradeMethods": [
          "InstaPay"
        ]
      },
      "SELL": {
        "price": 51.09,
        "pickedIndex": 1,
        "availableRows": 11,
        "advNo": "12845658446082236416",
        "nickName": "__G__A__N__A__A__T__",
        "minSingleTransAmount": "100",
        "maxSingleTransAmount": "101",
        "tradeMethods": [
          "Vodafone cash"
        ]
      }
    },
    "AED": {
      "BUY": {
        "price": 3.673,
        "pickedIndex": 1,
        "availableRows": 10,
        "advNo": "12905618127946551296",
        "nickName": "Trades unlimited ",
        "minSingleTransAmount": "5000",
        "maxSingleTransAmount": "25000",
        "tradeMethods": [
          "Abu Dhabi Commercial Bank ADCB",
          "Bank Transfer (Middle East)",
          "Bank Transfer"
        ]
      },
      "SELL": {
        "price": 3.664,
        "pickedIndex": 1,
        "availableRows": 10,
        "advNo": "12895980924805402624",
        "nickName": "Issasalim",
        "minSingleTransAmount": "24500",
        "maxSingleTransAmount": "25000",
        "tradeMethods": [
          "Cash Deposit to Bank"
        ]
      }
    },
    "SAR": {
      "BUY": {
        "price": 3.8,
        "pickedIndex": 1,
        "availableRows": 11,
        "advNo": "13908635684390006784",
        "nickName": "طــــــويـــــق",
        "minSingleTransAmount": "10000",
        "maxSingleTransAmount": "150000",
        "tradeMethods": [
          "Al Rajhi Bank",
          "Saudi National Bank (AlAhli Bank)"
        ]
      },
      "SELL": {
        "price": 3.84,
        "pickedIndex": 1,
        "availableRows": 11,
        "advNo": "12908639479810805760",
        "nickName": "HMIp2p",
        "minSingleTransAmount": "1000",
        "maxSingleTransAmount": "2200",
        "tradeMethods": [
          "Alinma Bank",
          "Saudi National Bank (AlAhli Bank)"
        ]
      }
    },
    "USD": {
      "BUY": {
        "price": 0.996,
        "pickedIndex": 1,
        "availableRows": 10,
        "advNo": "12908895537548005376",
        "nickName": "vesel11",
        "minSingleTransAmount": "4000",
        "maxSingleTransAmount": "5000",
        "tradeMethods": [
          "Bank of Georgia"
        ]
      },
      "SELL": {
        "price": 1.1,
        "pickedIndex": 1,
        "availableRows": 11,
        "advNo": "12907804740866424832",
        "nickName": "SKTradersZ",
        "minSingleTransAmount": "15",
        "maxSingleTransAmount": "5000",
        "tradeMethods": [
          "Google Pay (GPay)",
          "IMPS",
          "Paytm",
          "PhonePe",
          "Easypaisa-PK Only"
        ]
      }
    },
    "EUR": {
      "BUY": {
        "price": 0.884,
        "pickedIndex": 1,
        "availableRows": 11,
        "advNo": "12908576680668270592",
        "nickName": "P2P-ed7d08hs",
        "minSingleTransAmount": "89",
        "maxSingleTransAmount": "600",
        "tradeMethods": [
          "Wise"
        ]
      },
      "SELL": {
        "price": 0.957,
        "pickedIndex": 1,
        "availableRows": 11,
        "advNo": "12908899798877323264",
        "nickName": "majubesama",
        "minSingleTransAmount": "3500",
        "maxSingleTransAmount": "13569",
        "tradeMethods": [
          "Bank Transfer",
          "ZEN",
          "BBVA",
          "N26",
          "SEPA Instant"
        ]
      }
    }
  }
}