{
  "updatedAt": 1773770813180,
  "source": "Binance P2P web endpoint",
  "asset": "USDT",
  "prices": {
    "OMR": {
      "BUY": {
        "price": 0.39,
        "pickedIndex": 1,
        "availableRows": 11,
        "advNo": "12862597317894311936",
        "nickName": "BASEL-L",
        "minSingleTransAmount": "300",
        "maxSingleTransAmount": "2500",
        "tradeMethods": [
          "Sohar International"
        ]
      },
      "SELL": {
        "price": 0.39,
        "pickedIndex": 1,
        "availableRows": 11,
        "advNo": "12836464470759849984",
        "nickName": "Ammar50005",
        "minSingleTransAmount": "2499",
        "maxSingleTransAmount": "2500",
        "tradeMethods": [
          "Oman Arab Bank",
          "Bank Transfer (Middle East)",
          "Bank Muscat",
          "Airtime Mobile Top-Up"
        ]
      }
    },
    "EGP": {
      "BUY": {
        "price": 52.31,
        "pickedIndex": 1,
        "availableRows": 11,
        "advNo": "13675162589774381056",
        "nickName": "aboobida82",
        "minSingleTransAmount": "12000",
        "maxSingleTransAmount": "12001",
        "tradeMethods": [
          "InstaPay",
          "Banque Misr"
        ]
      },
      "SELL": {
        "price": 52.55,
        "pickedIndex": 1,
        "availableRows": 11,
        "advNo": "12846632843843330048",
        "nickName": "__mng__",
        "minSingleTransAmount": "50000",
        "maxSingleTransAmount": "50001",
        "tradeMethods": [
          "Etisalat Cash"
        ]
      }
    },
    "AED": {
      "BUY": {
        "price": 3.695,
        "pickedIndex": 1,
        "availableRows": 10,
        "advNo": "12866586150936059904",
        "nickName": "Mohammad_Ahmad1",
        "minSingleTransAmount": "500",
        "maxSingleTransAmount": "20000",
        "tradeMethods": [
          "Bank Transfer"
        ]
      },
      "SELL": {
        "price": 3.683,
        "pickedIndex": 1,
        "availableRows": 10,
        "advNo": "12867132132117639168",
        "nickName": "Tᴏƙʏσ Tʀᴀᴅɛʀ ™",
        "minSingleTransAmount": "14000",
        "maxSingleTransAmount": "15000",
        "tradeMethods": [
          "Cash Deposit to Bank",
          "Emirates NBD"
        ]
      }
    },
    "SAR": {
      "BUY": {
        "price": 3.82,
        "pickedIndex": 1,
        "availableRows": 11,
        "advNo": "13855445227543060480",
        "nickName": "Al-habsi",
        "minSingleTransAmount": "2759",
        "maxSingleTransAmount": "2760",
        "tradeMethods": [
          "Bank Transfer",
          "Arab Bank"
        ]
      },
      "SELL": {
        "price": 3.92,
        "pickedIndex": 1,
        "availableRows": 11,
        "advNo": "12860993954605244416",
        "nickName": "dr_tiger",
        "minSingleTransAmount": "190",
        "maxSingleTransAmount": "190",
        "tradeMethods": [
          "Saudi National Bank (AlAhli Bank)",
          "Al Rajhi Bank",
          "Alinma Bank"
        ]
      }
    },
    "USD": {
      "BUY": {
        "price": 0.996,
        "pickedIndex": 1,
        "availableRows": 11,
        "advNo": "13866154645479104512",
        "nickName": "SpeedyXchange",
        "minSingleTransAmount": "50",
        "maxSingleTransAmount": "400",
        "tradeMethods": [
          "AirTM"
        ]
      },
      "SELL": {
        "price": 1.1,
        "pickedIndex": 1,
        "availableRows": 11,
        "advNo": "12837566109293064192",
        "nickName": "Rurisyz",
        "minSingleTransAmount": "500",
        "maxSingleTransAmount": "6800",
        "tradeMethods": [
          "SEA Bank"
        ]
      }
    },
    "EUR": {
      "BUY": {
        "price": 0.87,
        "pickedIndex": 1,
        "availableRows": 11,
        "advNo": "13849127982920032256",
        "nickName": "Novudi",
        "minSingleTransAmount": "800",
        "maxSingleTransAmount": "100000",
        "tradeMethods": [
          "SEPA Instant",
          "SEPA (EU) bank transfer",
          "Bank Transfer",
          "BBVA"
        ]
      },
      "SELL": {
        "price": 0.918,
        "pickedIndex": 1,
        "availableRows": 11,
        "advNo": "12866571411465371648",
        "nickName": "Anyelithcuellar",
        "minSingleTransAmount": "29800",
        "maxSingleTransAmount": "29900",
        "tradeMethods": [
          "Banco Santander (Spain)",
          "SEPA Instant",
          "N26",
          "BBVA",
          "ING"
        ]
      }
    }
  }
}