{
  "updatedAt": 1784024627459,
  "source": "Binance P2P web endpoint",
  "asset": "USDT",
  "prices": {
    "OMR": {
      "BUY": {
        "price": 0.39,
        "pickedIndex": 1,
        "availableRows": 11,
        "advNo": "13906418868802232320",
        "nickName": "CryptoAnalysts",
        "minSingleTransAmount": "200",
        "maxSingleTransAmount": "10000",
        "tradeMethods": [
          "Bank Muscat",
          "Bank Dhofar",
          "Ahlibank"
        ]
      },
      "SELL": {
        "price": 0.391,
        "pickedIndex": 1,
        "availableRows": 11,
        "advNo": "12908812741908590592",
        "nickName": "Abdullah20002",
        "minSingleTransAmount": "2000",
        "maxSingleTransAmount": "2500",
        "tradeMethods": [
          "Bank Transfer"
        ]
      }
    },
    "EGP": {
      "BUY": {
        "price": 51.44,
        "pickedIndex": 1,
        "availableRows": 11,
        "advNo": "12910258488845766656",
        "nickName": "captainzizo",
        "minSingleTransAmount": "15000",
        "maxSingleTransAmount": "15000",
        "tradeMethods": [
          "InstaPay"
        ]
      },
      "SELL": {
        "price": 51.77,
        "pickedIndex": 1,
        "availableRows": 11,
        "advNo": "12750740641573056512",
        "nickName": "AMROOOUSY",
        "minSingleTransAmount": "4295",
        "maxSingleTransAmount": "4296",
        "tradeMethods": [
          "Vodafone cash"
        ]
      }
    },
    "AED": {
      "BUY": {
        "price": 3.665,
        "pickedIndex": 1,
        "availableRows": 10,
        "advNo": "13901292012014768128",
        "nickName": "HappyCryptoAE",
        "minSingleTransAmount": "5000",
        "maxSingleTransAmount": "150000",
        "tradeMethods": [
          "Bank Transfer",
          "Abu Dhabi Commercial Bank ADCB",
          "ADIB: Abu Dhabi Islamic Bank",
          "mBank",
          "Emirates NBD"
        ]
      },
      "SELL": {
        "price": 3.66,
        "pickedIndex": 1,
        "availableRows": 10,
        "advNo": "12908021321333727232",
        "nickName": "KB__TrustEx",
        "minSingleTransAmount": "2095",
        "maxSingleTransAmount": "2098",
        "tradeMethods": [
          "Aani"
        ]
      }
    },
    "SAR": {
      "BUY": {
        "price": 3.8,
        "pickedIndex": 1,
        "availableRows": 11,
        "advNo": "12909996751671382016",
        "nickName": "Aboslman1",
        "minSingleTransAmount": "5000",
        "maxSingleTransAmount": "100000",
        "tradeMethods": [
          "Alinma Bank",
          "Saudi National Bank (AlAhli Bank)"
        ]
      },
      "SELL": {
        "price": 3.86,
        "pickedIndex": 1,
        "availableRows": 11,
        "advNo": "12805484221358727168",
        "nickName": "Nawaf",
        "minSingleTransAmount": "150",
        "maxSingleTransAmount": "188",
        "tradeMethods": [
          "AlinmaPay",
          "Mobily Pay",
          "Bank Transfer",
          "stc pay",
          "urpay"
        ]
      }
    },
    "USD": {
      "BUY": {
        "price": 0.998,
        "pickedIndex": 1,
        "availableRows": 11,
        "advNo": "12909720043299000320",
        "nickName": "CryptoRapidoySeguro1",
        "minSingleTransAmount": "15",
        "maxSingleTransAmount": "50",
        "tradeMethods": [
          "Produbanco",
          "Banco Bolivariano",
          "Banco del pacifico"
        ]
      },
      "SELL": {
        "price": 1.1,
        "pickedIndex": 1,
        "availableRows": 11,
        "advNo": "12909294095091351552",
        "nickName": "TakuVnzl",
        "minSingleTransAmount": "18",
        "maxSingleTransAmount": "20",
        "tradeMethods": [
          "Payme.io",
          "Paynet",
          "Paysera",
          "Paytm",
          "PayPro"
        ]
      }
    },
    "EUR": {
      "BUY": {
        "price": 0.884,
        "pickedIndex": 1,
        "availableRows": 11,
        "advNo": "13901792415399645184",
        "nickName": "Trustptop",
        "minSingleTransAmount": "100",
        "maxSingleTransAmount": "100000",
        "tradeMethods": [
          "Fastoo wallet",
          "Bank of Georgia",
          "TBC Bank"
        ]
      },
      "SELL": {
        "price": 0.91,
        "pickedIndex": 1,
        "availableRows": 11,
        "advNo": "12910021597498687488",
        "nickName": "Phoenix_Change",
        "minSingleTransAmount": "1165",
        "maxSingleTransAmount": "1165",
        "tradeMethods": [
          "Banco Santander (Spain)",
          "Bizum",
          "Bank Transfer",
          "SEPA (EU) bank transfer",
          "BBVA"
        ]
      }
    }
  }
}