{
  "updatedAt": 1774713175054,
  "source": "Binance P2P web endpoint",
  "asset": "USDT",
  "prices": {
    "OMR": {
      "BUY": {
        "price": 0.393,
        "pickedIndex": 1,
        "availableRows": 11,
        "advNo": "12859733042922000384",
        "nickName": "Ali-Crypto22",
        "minSingleTransAmount": "300",
        "maxSingleTransAmount": "2500",
        "tradeMethods": [
          "Bank Muscat",
          "Sohar International",
          "Ahlibank"
        ]
      },
      "SELL": {
        "price": 0.404,
        "pickedIndex": 1,
        "availableRows": 11,
        "advNo": "12870541286956449792",
        "nickName": "Cryptoversee",
        "minSingleTransAmount": "600",
        "maxSingleTransAmount": "2500",
        "tradeMethods": [
          "Bank Transfer"
        ]
      }
    },
    "EGP": {
      "BUY": {
        "price": 53.16,
        "pickedIndex": 1,
        "availableRows": 11,
        "advNo": "13870950827358760960",
        "nickName": "XTrueDeal",
        "minSingleTransAmount": "1000",
        "maxSingleTransAmount": "1500",
        "tradeMethods": [
          "InstaPay"
        ]
      },
      "SELL": {
        "price": 53.55,
        "pickedIndex": 1,
        "availableRows": 11,
        "advNo": "12827669129974206464",
        "nickName": "ESNI00",
        "minSingleTransAmount": "5000",
        "maxSingleTransAmount": "5001",
        "tradeMethods": [
          "Vodafone cash"
        ]
      }
    },
    "AED": {
      "BUY": {
        "price": 3.711,
        "pickedIndex": 1,
        "availableRows": 10,
        "advNo": "12759233664740556800",
        "nickName": "McLaren19",
        "minSingleTransAmount": "20000",
        "maxSingleTransAmount": "25000",
        "tradeMethods": [
          "Bank Transfer"
        ]
      },
      "SELL": {
        "price": 3.698,
        "pickedIndex": 1,
        "availableRows": 10,
        "advNo": "12862705737686368256",
        "nickName": "MR_MOHAMED94",
        "minSingleTransAmount": "2300",
        "maxSingleTransAmount": "2301",
        "tradeMethods": [
          "Abu Dhabi Commercial Bank ADCB",
          "Bank Transfer"
        ]
      }
    },
    "SAR": {
      "BUY": {
        "price": 3.82,
        "pickedIndex": 1,
        "availableRows": 11,
        "advNo": "12871119686457716736",
        "nickName": "Ibrahim8008",
        "minSingleTransAmount": "10000",
        "maxSingleTransAmount": "100000",
        "tradeMethods": [
          "Al Rajhi Bank",
          "Saudi National Bank (AlAhli Bank)"
        ]
      },
      "SELL": {
        "price": 3.88,
        "pickedIndex": 1,
        "availableRows": 11,
        "advNo": "12870593881964769280",
        "nickName": "EH_Crypto_Nexus",
        "minSingleTransAmount": "60",
        "maxSingleTransAmount": "182",
        "tradeMethods": [
          "Al Rajhi Bank"
        ]
      }
    },
    "USD": {
      "BUY": {
        "price": 1.0,
        "pickedIndex": 1,
        "availableRows": 11,
        "advNo": "12556206845790932992",
        "nickName": "誌得其樂",
        "minSingleTransAmount": "15",
        "maxSingleTransAmount": "1500",
        "tradeMethods": [
          "Bank Transfer (Taiwan)"
        ]
      },
      "SELL": {
        "price": 1.1,
        "pickedIndex": 1,
        "availableRows": 11,
        "advNo": "12837566109293064192",
        "nickName": "Rurisyz",
        "minSingleTransAmount": "500",
        "maxSingleTransAmount": "6800",
        "tradeMethods": [
          "SEA Bank"
        ]
      }
    },
    "EUR": {
      "BUY": {
        "price": 0.872,
        "pickedIndex": 1,
        "availableRows": 10,
        "advNo": "13819385243161866240",
        "nickName": "PLUMEX",
        "minSingleTransAmount": "300",
        "maxSingleTransAmount": "100000",
        "tradeMethods": [
          "ZEN",
          "Bank Transfer",
          "SEPA (EU) bank transfer",
          "SEPA Instant",
          "N26"
        ]
      },
      "SELL": {
        "price": 0.932,
        "pickedIndex": 1,
        "availableRows": 11,
        "advNo": "12870787962465816576",
        "nickName": "Autobot077",
        "minSingleTransAmount": "7385",
        "maxSingleTransAmount": "34745",
        "tradeMethods": [
          "Paysera",
          "SEPA Instant",
          "N26",
          "ZEN",
          "BBVA"
        ]
      }
    }
  }
}