{
  "updatedAt": 1781363434186,
  "source": "Binance P2P web endpoint",
  "asset": "USDT",
  "prices": {
    "OMR": {
      "BUY": {
        "price": 0.389,
        "pickedIndex": 1,
        "availableRows": 11,
        "advNo": "12898993522815217664",
        "nickName": "KaluPay",
        "minSingleTransAmount": "500",
        "maxSingleTransAmount": "2500",
        "tradeMethods": [
          "Bank Muscat",
          "Bank Transfer",
          "Oman Arab Bank",
          "National Bank of Oman",
          "Bank Dhofar"
        ]
      },
      "SELL": {
        "price": 0.387,
        "pickedIndex": 1,
        "availableRows": 10,
        "advNo": "12895962728509267968",
        "nickName": "OMR_ALAA",
        "minSingleTransAmount": "200",
        "maxSingleTransAmount": "2500",
        "tradeMethods": [
          "Airtime Mobile Top-Up",
          "Bank Muscat",
          "Sohar International"
        ]
      }
    },
    "EGP": {
      "BUY": {
        "price": 52.77,
        "pickedIndex": 1,
        "availableRows": 11,
        "advNo": "12899129763109470208",
        "nickName": "Faraaag",
        "minSingleTransAmount": "5000",
        "maxSingleTransAmount": "5001",
        "tradeMethods": [
          "InstaPay"
        ]
      },
      "SELL": {
        "price": 53.2,
        "pickedIndex": 1,
        "availableRows": 11,
        "advNo": "12891381901845417984",
        "nickName": "The_captain1",
        "minSingleTransAmount": "25000",
        "maxSingleTransAmount": "25001",
        "tradeMethods": [
          "Vodafone cash"
        ]
      }
    },
    "AED": {
      "BUY": {
        "price": 3.675,
        "pickedIndex": 1,
        "availableRows": 10,
        "advNo": "13898713056413540352",
        "nickName": "BLOCKSY",
        "minSingleTransAmount": "5000",
        "maxSingleTransAmount": "700000",
        "tradeMethods": [
          "AL MASHREQ Bank",
          "Bank Transfer",
          "Bank Transfer (Middle East)"
        ]
      },
      "SELL": {
        "price": 3.665,
        "pickedIndex": 1,
        "availableRows": 10,
        "advNo": "12899127780897406976",
        "nickName": "P2P-3f6454sw",
        "minSingleTransAmount": "10000",
        "maxSingleTransAmount": "25000",
        "tradeMethods": [
          "Bank Transfer",
          "Cash Deposit to Bank"
        ]
      }
    },
    "SAR": {
      "BUY": {
        "price": 3.8,
        "pickedIndex": 1,
        "availableRows": 11,
        "advNo": "12897237175256588288",
        "nickName": "Abu-Abdullah999",
        "minSingleTransAmount": "1600",
        "maxSingleTransAmount": "1620",
        "tradeMethods": [
          "Al Rajhi Bank",
          "Bank Transfer",
          "barq",
          "Saudi National Bank (AlAhli Bank)",
          "Alinma Bank"
        ]
      },
      "SELL": {
        "price": 3.9,
        "pickedIndex": 1,
        "availableRows": 10,
        "advNo": "12894858958025961472",
        "nickName": "AL_Pharon",
        "minSingleTransAmount": "396",
        "maxSingleTransAmount": "396",
        "tradeMethods": [
          "Bank Transfer",
          "BenefitPay",
          "Alinma Bank",
          "Transfers with specific bank",
          "Al Rajhi Bank"
        ]
      }
    },
    "USD": {
      "BUY": {
        "price": 0.96,
        "pickedIndex": 1,
        "availableRows": 11,
        "advNo": "12899129691962712064",
        "nickName": "ngscorp",
        "minSingleTransAmount": "500",
        "maxSingleTransAmount": "3000",
        "tradeMethods": [
          "Banco General Panama"
        ]
      },
      "SELL": {
        "price": 1.1,
        "pickedIndex": 1,
        "availableRows": 11,
        "advNo": "12898960708637114368",
        "nickName": "leona69",
        "minSingleTransAmount": "195",
        "maxSingleTransAmount": "199",
        "tradeMethods": [
          "Zelle"
        ]
      }
    },
    "EUR": {
      "BUY": {
        "price": 0.868,
        "pickedIndex": 1,
        "availableRows": 10,
        "advNo": "13778894097322680320",
        "nickName": "VincitoreGroup",
        "minSingleTransAmount": "5000",
        "maxSingleTransAmount": "20000",
        "tradeMethods": [
          "SEPA Instant",
          "SEPA (EU) bank transfer",
          "Bunq",
          "Paysera",
          "Bank Transfer"
        ]
      },
      "SELL": {
        "price": 0.91,
        "pickedIndex": 1,
        "availableRows": 11,
        "advNo": "12888531355005026304",
        "nickName": "PROMETEY_MERCHANT",
        "minSingleTransAmount": "1400",
        "maxSingleTransAmount": "2000",
        "tradeMethods": [
          "Bank Transfer",
          "SEPA (EU) bank transfer"
        ]
      }
    }
  }
}